TSVZ.py
tsvz-3.35.dist-info/METADATA
tsvz-3.35.dist-info/WHEEL
tsvz-3.35.dist-info/entry_points.txt
tsvz-3.35.dist-info/top_level.txt
tsvz-3.35.dist-info/RECORD
